{
  "ability": "способность, возможность",
  "application": "просьба; заявление; форма заявления",
  "contradict": "противоречить",
  "fail": "недоставать, не хватать, иметь недостаток; истощаться, вырабатываться, растрачиваться",
  "fg": "мелкозернистый",
  "gg": "целевой градиент",
  "keep": "держать, не отдавать",
  "look": "взгляд",
  "looking": "обзор; поиск",
  "mind": "разум; умственные способности; ум",
  "over": "над, выше",
  "pl": "частичная гибель",
  "police": "полиция",
  "pp": "по доверенности",
  "ppp": "протокол передачи от точки к точке, протокол двухточечного соединения",
  "room": "комната; помещение",
  "soft": "мягкий",
  "trust": "вера, доверие",
  "uu": "микромикро-, пико-, 10 в минус 12-й степени",
  "xx": "без обеспечения или поручительства"
}
